replicon_handler.py
replicon_handler-1.1.7.dist-info/LICENSE
replicon_handler-1.1.7.dist-info/METADATA
replicon_handler-1.1.7.dist-info/WHEEL
replicon_handler-1.1.7.dist-info/top_level.txt
replicon_handler-1.1.7.dist-info/RECORD
